[
  {
    "id": "20250516-41I1F7000",
    "ngay": "20250516",
    "machungkhoan": "41I1F7000",
    "thamchieu": 1401.5,
    "mocua": 1395.1,
    "dongcua": 1385.9,
    "caonhat": 1405.1,
    "thapnhat": 1303.5,
    "biendogiaodong": 101.6,
    "phantrambiendogiaodong": 7.79,
    "khoiluong": "2446",
    "io": 347,
    "giathanhtoan": 1385.9,
    "khoiluongthoathuan": "0",
    "giatrithoathuan": "0",
    "khoiluongkhoplenh": "2446",
    "giatrikhoplenh": "339822740000",
    "thaydoisovoingaytruoc": -15.6,
    "phantramthaydoisovoingaytruoc": -1.11,
    "phantramgioihantrongngay": 0.07,
    "gioihancaonhat": 1492.76,
    "gioihanthapnhat": 1297.44,
    "thaydoi": -15.6,
    "phantramthaydoi": -1.11,
    "tongkhoiluong": "0",
    "giatran": 1499.6,
    "giasan": 1303.4,
    "tanggia": 10,
    "phantramtanggia": 0.72,
    "giamgia": 91.6,
    "phantramgiamgia": 6.61,
    "biendothaydoi": 101.6,
    "phantrambiendothaydoi": 7.33,
    "tongkhoiluongmua": "0",
    "tongkhoiluongban": "0"
  },
  {
    "id": "20250519-41I1F7000",
    "ngay": "20250519",
    "machungkhoan": "41I1F7000",
    "thamchieu": 1385.9,
    "mocua": 1376.1,
    "dongcua": 1379.2,
    "caonhat": 1391.9,
    "thapnhat": 1372,
    "biendogiaodong": 19.9,
    "phantrambiendogiaodong": 1.45,
    "khoiluong": "1352",
    "io": 347,
    "giathanhtoan": 1379.2,
    "khoiluongthoathuan": "0",
    "giatrithoathuan": "0",
    "khoiluongkhoplenh": "1352",
    "giatrikhoplenh": "186881290000",
    "thaydoisovoingaytruoc": -6.7,
    "phantramthaydoisovoingaytruoc": -0.48,
    "phantramgioihantrongngay": 0.07,
    "gioihancaonhat": 1472.43,
    "gioihanthapnhat": 1279.77,
    "thaydoi": -6.7,
    "phantramthaydoi": -0.48,
    "tongkhoiluong": "722",
    "giatran": 1482.9,
    "giasan": 1288.9,
    "tanggia": 15.8,
    "phantramtanggia": 1.15,
    "giamgia": 4.1,
    "phantramgiamgia": 0.3,
    "biendothaydoi": 19.9,
    "phantrambiendothaydoi": 1.45,
    "tongkhoiluongmua": "354",
    "tongkhoiluongban": "368"
  },
  {
    "id": "20250520-41I1F7000",
    "ngay": "20250520",
    "machungkhoan": "41I1F7000",
    "thamchieu": 1379.2,
    "mocua": 1382.2,
    "dongcua": 1410,
    "caonhat": 1414.2,
    "thapnhat": 1382.1,
    "biendogiaodong": 32.1,
    "phantrambiendogiaodong": 2.32,
    "khoiluong": "926",
    "io": 562,
    "giathanhtoan": 1410,
    "khoiluongthoathuan": "0",
    "giatrithoathuan": "0",
    "khoiluongkhoplenh": "926",
    "giatrikhoplenh": "129487740000",
    "thaydoisovoingaytruoc": 30.8,
    "phantramthaydoisovoingaytruoc": 2.23,
    "phantramgioihantrongngay": 0.07,
    "gioihancaonhat": 1478.95,
    "gioihanthapnhat": 1285.45,
    "thaydoi": 30.8,
    "phantramthaydoi": 2.23,
    "tongkhoiluong": "534",
    "giatran": 1475.7,
    "giasan": 1282.7,
    "tanggia": 32,
    "phantramtanggia": 2.27,
    "giamgia": 0.1,
    "phantramgiamgia": 0.01,
    "biendothaydoi": 32.1,
    "phantrambiendothaydoi": 2.28,
    "tongkhoiluongmua": "230",
    "tongkhoiluongban": "304"
  },
  {
    "id": "20250521-41I1F7000",
    "ngay": "20250521",
    "machungkhoan": "41I1F7000",
    "thamchieu": 1410,
    "mocua": 1406.5,
    "dongcua": 1414.1,
    "caonhat": 1422.8,
    "thapnhat": 1406.5,
    "biendogiaodong": 16.3,
    "phantrambiendogiaodong": 1.16,
    "khoiluong": "956",
    "io": 728,
    "giathanhtoan": 1414.1,
    "khoiluongthoathuan": "0",
    "giatrithoathuan": "0",
    "khoiluongkhoplenh": "956",
    "giatrikhoplenh": "135178200000",
    "thaydoisovoingaytruoc": 4.1,
    "phantramthaydoisovoingaytruoc": 0.29,
    "phantramgioihantrongngay": 0.07,
    "gioihancaonhat": 1504.96,
    "gioihanthapnhat": 1308.04,
    "thaydoi": 4.1,
    "phantramthaydoi": 0.29,
    "tongkhoiluong": "537",
    "giatran": 1508.7,
    "giasan": 1311.3,
    "tanggia": 16.3,
    "phantramtanggia": 1.15,
    "giamgia": 0,
    "phantramgiamgia": 0,
    "biendothaydoi": 16.3,
    "phantrambiendothaydoi": 1.15,
    "tongkhoiluongmua": "227",
    "tongkhoiluongban": "310"
  },
  {
    "id": "20250522-41I1F7000",
    "ngay": "20250522",
    "machungkhoan": "41I1F7000",
    "thamchieu": 1414.1,
    "mocua": 1408,
    "dongcua": 1407.4,
    "caonhat": 1421,
    "thapnhat": 1407.4,
    "biendogiaodong": 13.6,
    "phantrambiendogiaodong": 0.97,
    "khoiluong": "590",
    "io": 811,
    "giathanhtoan": 1407.4,
    "khoiluongthoathuan": "0",
    "giatrithoathuan": "0",
    "khoiluongkhoplenh": "590",
    "giatrikhoplenh": "83332420000",
    "thaydoisovoingaytruoc": -6.7,
    "phantramthaydoisovoingaytruoc": -0.47,
    "phantramgioihantrongngay": 0.07,
    "gioihancaonhat": 1506.56,
    "gioihanthapnhat": 1309.44,
    "thaydoi": -6.7,
    "phantramthaydoi": -0.47,
    "tongkhoiluong": "388",
    "giatran": 1513,
    "giasan": 1315.2,
    "tanggia": 13,
    "phantramtanggia": 0.92,
    "giamgia": 0.6,
    "phantramgiamgia": 0.04,
    "biendothaydoi": 13.6,
    "phantrambiendothaydoi": 0.96,
    "tongkhoiluongmua": "233",
    "tongkhoiluongban": "155"
  },
  {
    "id": "20250523-41I1F7000",
    "ngay": "20250523",
    "machungkhoan": "41I1F7000",
    "thamchieu": 1407.4,
    "mocua": 1407.3,
    "dongcua": 1406,
    "caonhat": 1409,
    "thapnhat": 1400.6,
    "biendogiaodong": 8.4,
    "phantrambiendogiaodong": 0.6,
    "khoiluong": "307",
    "io": 796,
    "giathanhtoan": 1406,
    "khoiluongthoathuan": "0",
    "giatrithoathuan": "0",
    "khoiluongkhoplenh": "307",
    "giatrikhoplenh": "43134030000",
    "thaydoisovoingaytruoc": -1.4,
    "phantramthaydoisovoingaytruoc": -0.1,
    "phantramgioihantrongngay": 0.07,
    "gioihancaonhat": 1505.81,
    "gioihanthapnhat": 1308.79,
    "thaydoi": -1.4,
    "phantramthaydoi": -0.1,
    "tongkhoiluong": "205",
    "giatran": 1505.9,
    "giasan": 1308.9,
    "tanggia": 1.7,
    "phantramtanggia": 0.12,
    "giamgia": 6.7,
    "phantramgiamgia": 0.48,
    "biendothaydoi": 8.4,
    "phantrambiendothaydoi": 0.6,
    "tongkhoiluongmua": "84",
    "tongkhoiluongban": "121"
  },
  {
    "id": "20250526-41I1F7000",
    "ngay": "20250526",
    "machungkhoan": "41I1F7000",
    "thamchieu": 1406,
    "mocua": 1408,
    "dongcua": 1415.9,
    "caonhat": 1415.9,
    "thapnhat": 1361.2,
    "biendogiaodong": 54.7,
    "phantrambiendogiaodong": 4.02,
    "khoiluong": "1507",
    "io": 787,
    "giathanhtoan": 1415.9,
    "khoiluongthoathuan": "100",
    "giatrithoathuan": "14000000000",
    "khoiluongkhoplenh": "1407",
    "giatrikhoplenh": "195240880000",
    "thaydoisovoingaytruoc": 9.9,
    "phantramthaydoisovoingaytruoc": 0.7,
    "phantramgioihantrongngay": 0.07,
    "gioihancaonhat": 1506.56,
    "gioihanthapnhat": 1309.44,
    "thaydoi": 9.9,
    "phantramthaydoi": 0.7,
    "tongkhoiluong": "708",
    "giatran": 1504.4,
    "giasan": 1307.6,
    "tanggia": 7.9,
    "phantramtanggia": 0.56,
    "giamgia": 46.8,
    "phantramgiamgia": 3.31,
    "biendothaydoi": 54.7,
    "phantrambiendothaydoi": 3.87,
    "tongkhoiluongmua": "319",
    "tongkhoiluongban": "389"
  },
  {
    "id": "20250527-41I1F7000",
    "ngay": "20250527",
    "machungkhoan": "41I1F7000",
    "thamchieu": 1415.9,
    "mocua": 1416.5,
    "dongcua": 1414,
    "caonhat": 1419.4,
    "thapnhat": 1407.5,
    "biendogiaodong": 11.9,
    "phantrambiendogiaodong": 0.85,
    "khoiluong": "541",
    "io": 859,
    "giathanhtoan": 1414,
    "khoiluongthoathuan": "100",
    "giatrithoathuan": "14300000000",
    "khoiluongkhoplenh": "441",
    "giatrikhoplenh": "62324190000",
    "thaydoisovoingaytruoc": -1.9,
    "phantramthaydoisovoingaytruoc": -0.13,
    "phantramgioihantrongngay": 0.07,
    "gioihancaonhat": 1515.66,
    "gioihanthapnhat": 1317.34,
    "thaydoi": -1.9,
    "phantramthaydoi": -0.13,
    "tongkhoiluong": "298",
    "giatran": 1515,
    "giasan": 1316.8,
    "tanggia": 2.9,
    "phantramtanggia": 0.21,
    "giamgia": 9,
    "phantramgiamgia": 0.64,
    "biendothaydoi": 11.9,
    "phantrambiendothaydoi": 0.85,
    "tongkhoiluongmua": "83",
    "tongkhoiluongban": "215"
  },
  {
    "id": "20250528-41I1F7000",
    "ngay": "20250528",
    "machungkhoan": "41I1F7000",
    "thamchieu": 1414,
    "mocua": 1419.9,
    "dongcua": 1421.6,
    "caonhat": 1428,
    "thapnhat": 1419,
    "biendogiaodong": 9,
    "phantrambiendogiaodong": 0.63,
    "khoiluong": "782",
    "io": 1029,
    "giathanhtoan": 1421.6,
    "khoiluongthoathuan": "140",
    "giatrithoathuan": "20020000000",
    "khoiluongkhoplenh": "642",
    "giatrikhoplenh": "91373530000",
    "thaydoisovoingaytruoc": 7.6,
    "phantramthaydoisovoingaytruoc": 0.54,
    "phantramgioihantrongngay": 0.07,
    "gioihancaonhat": 1519.29,
    "gioihanthapnhat": 1320.51,
    "thaydoi": 7.6,
    "phantramthaydoi": 0.54,
    "tongkhoiluong": "341",
    "giatran": 1512.9,
    "giasan": 1315.1,
    "tanggia": 8.1,
    "phantramtanggia": 0.57,
    "giamgia": 0.9,
    "phantramgiamgia": 0.06,
    "biendothaydoi": 9,
    "phantrambiendothaydoi": 0.63,
    "tongkhoiluongmua": "143",
    "tongkhoiluongban": "198"
  },
  {
    "id": "20250529-41I1F7000",
    "ngay": "20250529",
    "machungkhoan": "41I1F7000",
    "thamchieu": 1421.6,
    "mocua": 1426.6,
    "dongcua": 1422,
    "caonhat": 1430.2,
    "thapnhat": 1417,
    "biendogiaodong": 13.2,
    "phantrambiendogiaodong": 0.93,
    "khoiluong": "483",
    "io": 1303,
    "giathanhtoan": 1422,
    "khoiluongthoathuan": "140",
    "giatrithoathuan": "20020000000",
    "khoiluongkhoplenh": "343",
    "giatrikhoplenh": "48843880000",
    "thaydoisovoingaytruoc": 0.4,
    "phantramthaydoisovoingaytruoc": 0.03,
    "phantramgioihantrongngay": 0.07,
    "gioihancaonhat": 1526.46,
    "gioihanthapnhat": 1326.74,
    "thaydoi": 0.4,
    "phantramthaydoi": 0.03,
    "tongkhoiluong": "162",
    "giatran": 1521.1,
    "giasan": 1322.1,
    "tanggia": 3.6,
    "phantramtanggia": 0.25,
    "giamgia": 9.6,
    "phantramgiamgia": 0.68,
    "biendothaydoi": 13.2,
    "phantrambiendothaydoi": 0.93,
    "tongkhoiluongmua": "90",
    "tongkhoiluongban": "72"
  },
  {
    "id": "20250530-41I1F7000",
    "ngay": "20250530",
    "machungkhoan": "41I1F7000",
    "thamchieu": 1422,
    "mocua": 1419.9,
    "dongcua": 1419.1,
    "caonhat": 1422,
    "thapnhat": 1415.1,
    "biendogiaodong": 6.9,
    "phantrambiendogiaodong": 0.49,
    "khoiluong": "438",
    "io": 1408,
    "giathanhtoan": 1419.1,
    "khoiluongthoathuan": "0",
    "giatrithoathuan": "0",
    "khoiluongkhoplenh": "438",
    "giatrikhoplenh": "62160320000",
    "thaydoisovoingaytruoc": -2.9,
    "phantramthaydoisovoingaytruoc": -0.2,
    "phantramgioihantrongngay": 0.07,
    "gioihancaonhat": 1519.29,
    "gioihanthapnhat": 1320.51,
    "thaydoi": -2.9,
    "phantramthaydoi": -0.2,
    "tongkhoiluong": "214",
    "giatran": 1521.5,
    "giasan": 1322.5,
    "tanggia": 2.1,
    "phantramtanggia": 0.15,
    "giamgia": 4.8,
    "phantramgiamgia": 0.34,
    "biendothaydoi": 6.9,
    "phantrambiendothaydoi": 0.49,
    "tongkhoiluongmua": "85",
    "tongkhoiluongban": "129"
  },
  {
    "id": "20250602-41I1F7000",
    "ngay": "20250602",
    "machungkhoan": "41I1F7000",
    "thamchieu": 1419.1,
    "mocua": 1413,
    "dongcua": 1411,
    "caonhat": 1417.5,
    "thapnhat": 1408.4,
    "biendogiaodong": 9.1,
    "phantrambiendogiaodong": 0.65,
    "khoiluong": "568",
    "io": 1677,
    "giathanhtoan": 1411,
    "khoiluongthoathuan": "100",
    "giatrithoathuan": "13800000000",
    "khoiluongkhoplenh": "468",
    "giatrikhoplenh": "66087050000",
    "thaydoisovoingaytruoc": -8.1,
    "phantramthaydoisovoingaytruoc": -0.57,
    "phantramgioihantrongngay": 0.07,
    "gioihancaonhat": 1511.91,
    "gioihanthapnhat": 1314.09,
    "thaydoi": -8.1,
    "phantramthaydoi": -0.57,
    "tongkhoiluong": "267",
    "giatran": 1518.4,
    "giasan": 1319.8,
    "tanggia": 4.5,
    "phantramtanggia": 0.32,
    "giamgia": 4.6,
    "phantramgiamgia": 0.33,
    "biendothaydoi": 9.1,
    "phantrambiendothaydoi": 0.65,
    "tongkhoiluongmua": "134",
    "tongkhoiluongban": "133"
  },
  {
    "id": "20250603-41I1F7000",
    "ngay": "20250603",
    "machungkhoan": "41I1F7000",
    "thamchieu": 1411,
    "mocua": 1416.9,
    "dongcua": 1434.4,
    "caonhat": 1440,
    "thapnhat": 1416.9,
    "biendogiaodong": 23.1,
    "phantrambiendogiaodong": 1.63,
    "khoiluong": "1028",
    "io": 1880,
    "giathanhtoan": 1434.4,
    "khoiluongthoathuan": "100",
    "giatrithoathuan": "14300000000",
    "khoiluongkhoplenh": "928",
    "giatrikhoplenh": "132737760000",
    "thaydoisovoingaytruoc": 23.4,
    "phantramthaydoisovoingaytruoc": 1.66,
    "phantramgioihantrongngay": 0.07,
    "gioihancaonhat": 1516.08,
    "gioihanthapnhat": 1317.72,
    "thaydoi": 23.4,
    "phantramthaydoi": 1.66,
    "tongkhoiluong": "529",
    "giatran": 1509.7,
    "giasan": 1312.3,
    "tanggia": 23.1,
    "phantramtanggia": 1.61,
    "giamgia": 0,
    "phantramgiamgia": 0,
    "biendothaydoi": 23.1,
    "phantrambiendothaydoi": 1.61,
    "tongkhoiluongmua": "272",
    "tongkhoiluongban": "257"
  },
  {
    "id": "20250604-41I1F7000",
    "ngay": "20250604",
    "machungkhoan": "41I1F7000",
    "thamchieu": 1434.4,
    "mocua": 1435.9,
    "dongcua": 1428.6,
    "caonhat": 1436,
    "thapnhat": 1425.8,
    "biendogiaodong": 10.2,
    "phantrambiendogiaodong": 0.72,
    "khoiluong": "380",
    "io": 2245,
    "giathanhtoan": 1428.6,
    "khoiluongthoathuan": "0",
    "giatrithoathuan": "0",
    "khoiluongkhoplenh": "380",
    "giatrikhoplenh": "54415270000",
    "thaydoisovoingaytruoc": -5.8,
    "phantramthaydoisovoingaytruoc": -0.4,
    "phantramgioihantrongngay": 0.07,
    "gioihancaonhat": 1536.41,
    "gioihanthapnhat": 1335.39,
    "thaydoi": -5.8,
    "phantramthaydoi": -0.4,
    "tongkhoiluong": "250",
    "giatran": 1534.8,
    "giasan": 1334,
    "tanggia": 0.1,
    "phantramtanggia": 0.01,
    "giamgia": 10.1,
    "phantramgiamgia": 0.71,
    "biendothaydoi": 10.2,
    "phantrambiendothaydoi": 0.72,
    "tongkhoiluongmua": "65",
    "tongkhoiluongban": "185"
  },
  {
    "id": "20250605-41I1F7000",
    "ngay": "20250605",
    "machungkhoan": "41I1F7000",
    "thamchieu": 1428.6,
    "mocua": 1428.5,
    "dongcua": 1425.6,
    "caonhat": 1430.2,
    "thapnhat": 1424.8,
    "biendogiaodong": 5.4,
    "phantrambiendogiaodong": 0.38,
    "khoiluong": "433",
    "io": 2416,
    "giathanhtoan": 1425.6,
    "khoiluongthoathuan": "0",
    "giatrithoathuan": "0",
    "khoiluongkhoplenh": "433",
    "giatrikhoplenh": "61796660000",
    "thaydoisovoingaytruoc": -3,
    "phantramthaydoisovoingaytruoc": -0.21,
    "phantramgioihantrongngay": 0.07,
    "gioihancaonhat": 1528.5,
    "gioihanthapnhat": 1328.5,
    "thaydoi": -3,
    "phantramthaydoi": -0.21,
    "tongkhoiluong": "260",
    "giatran": 1528.6,
    "giasan": 1328.6,
    "tanggia": 1.7,
    "phantramtanggia": 0.12,
    "giamgia": 3.7,
    "phantramgiamgia": 0.26,
    "biendothaydoi": 5.4,
    "phantrambiendothaydoi": 0.38,
    "tongkhoiluongmua": "71",
    "tongkhoiluongban": "189"
  },
  {
    "id": "20250606-41I1F7000",
    "ngay": "20250606",
    "machungkhoan": "41I1F7000",
    "thamchieu": 1425.6,
    "mocua": 1427,
    "dongcua": 1413,
    "caonhat": 1427,
    "thapnhat": 1411.8,
    "biendogiaodong": 15.2,
    "phantrambiendogiaodong": 1.08,
    "khoiluong": "531",
    "io": 2678,
    "giathanhtoan": 1413,
    "khoiluongthoathuan": "0",
    "giatrithoathuan": "0",
    "khoiluongkhoplenh": "531",
    "giatrikhoplenh": "75258490000",
    "thaydoisovoingaytruoc": -12.6,
    "phantramthaydoisovoingaytruoc": -0.88,
    "phantramgioihantrongngay": 0.07,
    "gioihancaonhat": 1526.89,
    "gioihanthapnhat": 1327.11,
    "thaydoi": -12.6,
    "phantramthaydoi": -0.88,
    "tongkhoiluong": "309",
    "giatran": 1525.3,
    "giasan": 1325.9,
    "tanggia": 0,
    "phantramtanggia": 0,
    "giamgia": 15.2,
    "phantramgiamgia": 1.08,
    "biendothaydoi": 15.2,
    "phantrambiendothaydoi": 1.08,
    "tongkhoiluongmua": "145",
    "tongkhoiluongban": "164"
  },
  {
    "id": "20250609-41I1F7000",
    "ngay": "20250609",
    "machungkhoan": "41I1F7000",
    "thamchieu": 1413,
    "mocua": 1417.4,
    "dongcua": 1399.9,
    "caonhat": 1417.4,
    "thapnhat": 1399.9,
    "biendogiaodong": 17.5,
    "phantrambiendogiaodong": 1.25,
    "khoiluong": "402",
    "io": 2755,
    "giathanhtoan": 1399.9,
    "khoiluongthoathuan": "0",
    "giatrithoathuan": "0",
    "khoiluongkhoplenh": "402",
    "giatrikhoplenh": "56619650000",
    "thaydoisovoingaytruoc": -13.1,
    "phantramthaydoisovoingaytruoc": -0.93,
    "phantramgioihantrongngay": 0.07,
    "gioihancaonhat": 1516.62,
    "gioihanthapnhat": 1318.18,
    "thaydoi": -13.1,
    "phantramthaydoi": -0.93,
    "tongkhoiluong": "0",
    "giatran": 1511.9,
    "giasan": 1314.1,
    "tanggia": 0,
    "phantramtanggia": 0,
    "giamgia": 17.5,
    "phantramgiamgia": 1.25,
    "biendothaydoi": 17.5,
    "phantrambiendothaydoi": 1.25,
    "tongkhoiluongmua": "121",
    "tongkhoiluongban": "151"
  },
  {
    "id": "20250610-41I1F7000",
    "ngay": "20250610",
    "machungkhoan": "41I1F7000",
    "thamchieu": 1399.9,
    "mocua": 1398,
    "dongcua": 1395.6,
    "caonhat": 1444,
    "thapnhat": 1392.4,
    "biendogiaodong": 51.6,
    "phantrambiendogiaodong": 3.71,
    "khoiluong": "1127",
    "io": 2839,
    "giathanhtoan": 1395.6,
    "khoiluongthoathuan": "0",
    "giatrithoathuan": "0",
    "khoiluongkhoplenh": "1127",
    "giatrikhoplenh": "158228440000",
    "thaydoisovoingaytruoc": -4.3,
    "phantramthaydoisovoingaytruoc": -0.31,
    "phantramgioihantrongngay": 0.07,
    "gioihancaonhat": 1495.86,
    "gioihanthapnhat": 1300.14,
    "thaydoi": -4.3,
    "phantramthaydoi": -0.31,
    "tongkhoiluong": "0",
    "giatran": 1497.8,
    "giasan": 1302,
    "tanggia": 46,
    "phantramtanggia": 3.3,
    "giamgia": 5.6,
    "phantramgiamgia": 0.4,
    "biendothaydoi": 51.6,
    "phantrambiendothaydoi": 3.7,
    "tongkhoiluongmua": "285",
    "tongkhoiluongban": "305"
  },
  {
    "id": "20250611-41I1F7000",
    "ngay": "20250611",
    "machungkhoan": "41I1F7000",
    "thamchieu": 1395.6,
    "mocua": 1400,
    "dongcua": 1400,
    "caonhat": 1402.5,
    "thapnhat": 1394.5,
    "biendogiaodong": 8,
    "phantrambiendogiaodong": 0.57,
    "khoiluong": "644",
    "io": 3188,
    "giathanhtoan": 1400,
    "khoiluongthoathuan": "0",
    "giatrithoathuan": "0",
    "khoiluongkhoplenh": "644",
    "giatrikhoplenh": "90107960000",
    "thaydoisovoingaytruoc": 4.4,
    "phantramthaydoisovoingaytruoc": 0.32,
    "phantramgioihantrongngay": 0.07,
    "gioihancaonhat": 1498,
    "gioihanthapnhat": 1302,
    "thaydoi": 4.4,
    "phantramthaydoi": 0.32,
    "tongkhoiluong": "0",
    "giatran": 1493.2,
    "giasan": 1298,
    "tanggia": 2.5,
    "phantramtanggia": 0.18,
    "giamgia": 5.5,
    "phantramgiamgia": 0.39,
    "biendothaydoi": 8,
    "phantrambiendothaydoi": 0.57,
    "tongkhoiluongmua": "125",
    "tongkhoiluongban": "250"
  },
  {
    "id": "20250612-41I1F7000",
    "ngay": "20250612",
    "machungkhoan": "41I1F7000",
    "thamchieu": 1400,
    "mocua": 1399.8,
    "dongcua": 1408,
    "caonhat": 1417.3,
    "thapnhat": 1399.6,
    "biendogiaodong": 17.7,
    "phantrambiendogiaodong": 1.26,
    "khoiluong": "1752",
    "io": 3600,
    "giathanhtoan": 1408,
    "khoiluongthoathuan": "0",
    "giatrithoathuan": "0",
    "khoiluongkhoplenh": "1752",
    "giatrikhoplenh": "247292740000",
    "thaydoisovoingaytruoc": 8,
    "phantramthaydoisovoingaytruoc": 0.57,
    "phantramgioihantrongngay": 0.07,
    "gioihancaonhat": 1497.79,
    "gioihanthapnhat": 1301.81,
    "thaydoi": 8,
    "phantramthaydoi": 0.57,
    "tongkhoiluong": "0",
    "giatran": 1498,
    "giasan": 1302,
    "tanggia": 17.5,
    "phantramtanggia": 1.24,
    "giamgia": 0.2,
    "phantramgiamgia": 0.01,
    "biendothaydoi": 17.7,
    "phantrambiendothaydoi": 1.25,
    "tongkhoiluongmua": "285",
    "tongkhoiluongban": "584"
  },
  {
    "id": "20250613-41I1F7000",
    "ngay": "20250613",
    "machungkhoan": "41I1F7000",
    "thamchieu": 1408,
    "mocua": 1399.5,
    "dongcua": 1392.9,
    "caonhat": 1399.5,
    "thapnhat": 1381,
    "biendogiaodong": 18.5,
    "phantrambiendogiaodong": 1.34,
    "khoiluong": "1564",
    "io": 4445,
    "giathanhtoan": 1392.9,
    "khoiluongthoathuan": "0",
    "giatrithoathuan": "0",
    "khoiluongkhoplenh": "1564",
    "giatrikhoplenh": "217769620000",
    "thaydoisovoingaytruoc": -15.1,
    "phantramthaydoisovoingaytruoc": -1.07,
    "phantramgioihantrongngay": 0.07,
    "gioihancaonhat": 1497.47,
    "gioihanthapnhat": 1301.53,
    "thaydoi": -15.1,
    "phantramthaydoi": -1.07,
    "tongkhoiluong": "0",
    "giatran": 1506.5,
    "giasan": 1309.5,
    "tanggia": 0,
    "phantramtanggia": 0,
    "giamgia": 18.5,
    "phantramgiamgia": 1.33,
    "biendothaydoi": 18.5,
    "phantrambiendothaydoi": 1.33,
    "tongkhoiluongmua": "388",
    "tongkhoiluongban": "484"
  },
  {
    "id": "20250616-41I1F7000",
    "ngay": "20250616",
    "machungkhoan": "41I1F7000",
    "thamchieu": 1392.9,
    "mocua": 1398.6,
    "dongcua": 1415.5,
    "caonhat": 1415.5,
    "thapnhat": 1393.2,
    "biendogiaodong": 22.3,
    "phantrambiendogiaodong": 1.6,
    "khoiluong": "5137",
    "io": 5148,
    "giathanhtoan": 1415.5,
    "khoiluongthoathuan": "0",
    "giatrithoathuan": "0",
    "khoiluongkhoplenh": "5137",
    "giatrikhoplenh": "720604800000",
    "thaydoisovoingaytruoc": 22.6,
    "phantramthaydoisovoingaytruoc": 1.62,
    "phantramgioihantrongngay": 0.07,
    "gioihancaonhat": 1496.5,
    "gioihanthapnhat": 1300.7,
    "thaydoi": 22.6,
    "phantramthaydoi": 1.62,
    "tongkhoiluong": "0",
    "giatran": 1490.4,
    "giasan": 1295.4,
    "tanggia": 16.9,
    "phantramtanggia": 1.19,
    "giamgia": 5.4,
    "phantramgiamgia": 0.38,
    "biendothaydoi": 22.3,
    "phantrambiendothaydoi": 1.57,
    "tongkhoiluongmua": "1182",
    "tongkhoiluongban": "1251"
  },
  {
    "id": "20250617-41I1F7000",
    "ngay": "20250617",
    "machungkhoan": "41I1F7000",
    "thamchieu": 1415.5,
    "mocua": 1418,
    "dongcua": 1420.5,
    "caonhat": 1426,
    "thapnhat": 1415,
    "biendogiaodong": 11,
    "phantrambiendogiaodong": 0.78,
    "khoiluong": "6416",
    "io": 8746,
    "giathanhtoan": 1420.5,
    "khoiluongthoathuan": "0",
    "giatrithoathuan": "0",
    "khoiluongkhoplenh": "6416",
    "giatrikhoplenh": "911223830000",
    "thaydoisovoingaytruoc": 5,
    "phantramthaydoisovoingaytruoc": 0.35,
    "phantramgioihantrongngay": 0.07,
    "gioihancaonhat": 1517.26,
    "gioihanthapnhat": 1318.74,
    "thaydoi": 5,
    "phantramthaydoi": 0.35,
    "tongkhoiluong": "0",
    "giatran": 1514.5,
    "giasan": 1316.5,
    "tanggia": 8,
    "phantramtanggia": 0.56,
    "giamgia": 3,
    "phantramgiamgia": 0.21,
    "biendothaydoi": 11,
    "phantrambiendothaydoi": 0.77,
    "tongkhoiluongmua": "1398",
    "tongkhoiluongban": "1333"
  },
  {
    "id": "20250618-41I1F7000",
    "ngay": "20250618",
    "machungkhoan": "41I1F7000",
    "thamchieu": 1420.5,
    "mocua": 1422.8,
    "dongcua": 1424,
    "caonhat": 1427.5,
    "thapnhat": 1419.8,
    "biendogiaodong": 7.7,
    "phantrambiendogiaodong": 0.54,
    "khoiluong": "11420",
    "io": 11981,
    "giathanhtoan": 1424,
    "khoiluongthoathuan": "0",
    "giatrithoathuan": "0",
    "khoiluongkhoplenh": "11420",
    "giatrikhoplenh": "1625443260000",
    "thaydoisovoingaytruoc": 3.5,
    "phantramthaydoisovoingaytruoc": 0.25,
    "phantramgioihantrongngay": 0.07,
    "gioihancaonhat": 1522.4,
    "gioihanthapnhat": 1323.2,
    "thaydoi": 3.5,
    "phantramthaydoi": 0.25,
    "tongkhoiluong": "0",
    "giatran": 1519.9,
    "giasan": 1321.1,
    "tanggia": 4.7,
    "phantramtanggia": 0.33,
    "giamgia": 3,
    "phantramgiamgia": 0.21,
    "biendothaydoi": 7.7,
    "phantrambiendothaydoi": 0.54,
    "tongkhoiluongmua": "3110",
    "tongkhoiluongban": "2462"
  },
  {
    "id": "20250619-41I1F7000",
    "ngay": "20250619",
    "machungkhoan": "41I1F7000",
    "thamchieu": 1424,
    "mocua": 1425.3,
    "dongcua": 1424,
    "caonhat": 1425.9,
    "thapnhat": 1419.2,
    "biendogiaodong": 6.7,
    "phantrambiendogiaodong": 0.47,
    "khoiluong": "21864",
    "io": 17316,
    "giathanhtoan": 1424,
    "khoiluongthoathuan": "0",
    "giatrithoathuan": "0",
    "khoiluongkhoplenh": "21864",
    "giatrikhoplenh": "3110430320000",
    "thaydoisovoingaytruoc": null,
    "phantramthaydoisovoingaytruoc": null,
    "phantramgioihantrongngay": 0.07,
    "gioihancaonhat": 1525.07,
    "gioihanthapnhat": 1325.53,
    "thaydoi": null,
    "phantramthaydoi": null,
    "tongkhoiluong": "0",
    "giatran": 1523.6,
    "giasan": 1324.4,
    "tanggia": 0.6,
    "phantramtanggia": 0.04,
    "giamgia": 6.1,
    "phantramgiamgia": 0.43,
    "biendothaydoi": 6.7,
    "phantrambiendothaydoi": 0.47,
    "tongkhoiluongmua": "5643",
    "tongkhoiluongban": "2792"
  },
  {
    "id": "20250620-41I1F7000",
    "ngay": "20250620",
    "machungkhoan": "41I1F7000",
    "thamchieu": 1424,
    "mocua": 1426.8,
    "dongcua": 1424.2,
    "caonhat": 1429.8,
    "thapnhat": 1420.5,
    "biendogiaodong": 9.3,
    "phantrambiendogiaodong": 0.65,
    "khoiluong": "141550",
    "io": 25836,
    "giathanhtoan": 1424.2,
    "khoiluongthoathuan": "2",
    "giatrithoathuan": "284800000",
    "khoiluongkhoplenh": "141548",
    "giatrikhoplenh": "20189406750000",
    "thaydoisovoingaytruoc": 0.2,
    "phantramthaydoisovoingaytruoc": 0.01,
    "phantramgioihantrongngay": 0.07,
    "gioihancaonhat": 1526.68,
    "gioihanthapnhat": 1326.92,
    "thaydoi": 0.2,
    "phantramthaydoi": 0.01,
    "tongkhoiluong": "0",
    "giatran": 1523.6,
    "giasan": 1324.4,
    "tanggia": 3,
    "phantramtanggia": 0.21,
    "giamgia": 6.3,
    "phantramgiamgia": 0.44,
    "biendothaydoi": 9.3,
    "phantrambiendothaydoi": 0.65,
    "tongkhoiluongmua": "14753",
    "tongkhoiluongban": "14540"
  },
  {
    "id": "20250623-41I1F7000",
    "ngay": "20250623",
    "machungkhoan": "41I1F7000",
    "thamchieu": 1424.2,
    "mocua": 1418,
    "dongcua": 1433.6,
    "caonhat": 1435.6,
    "thapnhat": 1414,
    "biendogiaodong": 21.6,
    "phantrambiendogiaodong": 1.53,
    "khoiluong": "191589",
    "io": 39301,
    "giathanhtoan": 1433.6,
    "khoiluongthoathuan": "0",
    "giatrithoathuan": "0",
    "khoiluongkhoplenh": "191589",
    "giatrikhoplenh": "27298967420000",
    "thaydoisovoingaytruoc": 9.4,
    "phantramthaydoisovoingaytruoc": 0.66,
    "phantramgioihantrongngay": 0.07,
    "gioihancaonhat": 1517.26,
    "gioihanthapnhat": 1318.74,
    "thaydoi": 9.4,
    "phantramthaydoi": 0.66,
    "tongkhoiluong": "0",
    "giatran": 1523.8,
    "giasan": 1324.6,
    "tanggia": 17.6,
    "phantramtanggia": 1.23,
    "giamgia": 4,
    "phantramgiamgia": 0.28,
    "biendothaydoi": 21.6,
    "phantrambiendothaydoi": 1.51,
    "tongkhoiluongmua": "16115",
    "tongkhoiluongban": "15582"
  },
  {
    "id": "20250624-41I1F7000",
    "ngay": "20250624",
    "machungkhoan": "41I1F7000",
    "thamchieu": 1433.6,
    "mocua": 1444,
    "dongcua": 1449,
    "caonhat": 1461,
    "thapnhat": 1443.2,
    "biendogiaodong": 17.8,
    "phantrambiendogiaodong": 1.23,
    "khoiluong": "200002",
    "io": 41230,
    "giathanhtoan": 1449,
    "khoiluongthoathuan": "0",
    "giatrithoathuan": "0",
    "khoiluongkhoplenh": "200002",
    "giatrikhoplenh": "29039450690000",
    "thaydoisovoingaytruoc": 15.4,
    "phantramthaydoisovoingaytruoc": 1.07,
    "phantramgioihantrongngay": 0.07,
    "gioihancaonhat": 1545.08,
    "gioihanthapnhat": 1342.92,
    "thaydoi": 15.4,
    "phantramthaydoi": 1.07,
    "tongkhoiluong": "0",
    "giatran": 1533.9,
    "giasan": 1333.3,
    "tanggia": 17,
    "phantramtanggia": 1.17,
    "giamgia": 0.8,
    "phantramgiamgia": 0.06,
    "biendothaydoi": 17.8,
    "phantrambiendothaydoi": 1.23,
    "tongkhoiluongmua": "17160",
    "tongkhoiluongban": "17564"
  },
  {
    "id": "20250625-41I1F7000",
    "ngay": "20250625",
    "machungkhoan": "41I1F7000",
    "thamchieu": 1449,
    "mocua": 1451.9,
    "dongcua": 1450.2,
    "caonhat": 1457.6,
    "thapnhat": 1446.3,
    "biendogiaodong": 11.3,
    "phantrambiendogiaodong": 0.78,
    "khoiluong": "159740",
    "io": 50293,
    "giathanhtoan": 1450.2,
    "khoiluongthoathuan": "0",
    "giatrithoathuan": "0",
    "khoiluongkhoplenh": "159740",
    "giatrikhoplenh": "23194494140000",
    "thaydoisovoingaytruoc": 1.2,
    "phantramthaydoisovoingaytruoc": 0.08,
    "phantramgioihantrongngay": 0.07,
    "gioihancaonhat": 1553.53,
    "gioihanthapnhat": 1350.27,
    "thaydoi": 1.2,
    "phantramthaydoi": 0.08,
    "tongkhoiluong": "0",
    "giatran": 1550.4,
    "giasan": 1347.6,
    "tanggia": 5.7,
    "phantramtanggia": 0.39,
    "giamgia": 5.6,
    "phantramgiamgia": 0.39,
    "biendothaydoi": 11.3,
    "phantrambiendothaydoi": 0.78,
    "tongkhoiluongmua": "0",
    "tongkhoiluongban": "0"
  },
  {
    "id": "20250626-41I1F7000",
    "ngay": "20250626",
    "machungkhoan": "41I1F7000",
    "thamchieu": 1450.2,
    "mocua": 1449.7,
    "dongcua": 1448.8,
    "caonhat": 1457.7,
    "thapnhat": 1447.1,
    "biendogiaodong": 10.6,
    "phantrambiendogiaodong": 0.73,
    "khoiluong": "142725",
    "io": 47696,
    "giathanhtoan": 1448.8,
    "khoiluongthoathuan": "20",
    "giatrithoathuan": "2870000000",
    "khoiluongkhoplenh": "142705",
    "giatrikhoplenh": "20717833720000",
    "thaydoisovoingaytruoc": -1.4,
    "phantramthaydoisovoingaytruoc": -0.1,
    "phantramgioihantrongngay": 0.07,
    "gioihancaonhat": 1551.18,
    "gioihanthapnhat": 1348.22,
    "thaydoi": -1.4,
    "phantramthaydoi": -0.1,
    "tongkhoiluong": "0",
    "giatran": 1551.7,
    "giasan": 1348.7,
    "tanggia": 8,
    "phantramtanggia": 0.55,
    "giamgia": 2.6,
    "phantramgiamgia": 0.18,
    "biendothaydoi": 10.6,
    "phantrambiendothaydoi": 0.73,
    "tongkhoiluongmua": "14626",
    "tongkhoiluongban": "14993"
  },
  {
    "id": "20250627-41I1F7000",
    "ngay": "20250627",
    "machungkhoan": "41I1F7000",
    "thamchieu": 1448.8,
    "mocua": 1453.2,
    "dongcua": 1460,
    "caonhat": 1463.5,
    "thapnhat": 1448.7,
    "biendogiaodong": 14.8,
    "phantrambiendogiaodong": 1.02,
    "khoiluong": "175539",
    "io": 44897,
    "giathanhtoan": 1460,
    "khoiluongthoathuan": "0",
    "giatrithoathuan": "0",
    "khoiluongkhoplenh": "175539",
    "giatrikhoplenh": "25554624850000",
    "thaydoisovoingaytruoc": 11.2,
    "phantramthaydoisovoingaytruoc": 0.77,
    "phantramgioihantrongngay": 0.07,
    "gioihancaonhat": 1554.92,
    "gioihanthapnhat": 1351.48,
    "thaydoi": 11.2,
    "phantramthaydoi": 0.77,
    "tongkhoiluong": "0",
    "giatran": 1550.2,
    "giasan": 1347.4,
    "tanggia": 10.3,
    "phantramtanggia": 0.71,
    "giamgia": 4.5,
    "phantramgiamgia": 0.31,
    "biendothaydoi": 14.8,
    "phantrambiendothaydoi": 1.02,
    "tongkhoiluongmua": "15853",
    "tongkhoiluongban": "16194"
  },
  {
    "id": "20250630-41I1F7000",
    "ngay": "20250630",
    "machungkhoan": "41I1F7000",
    "thamchieu": 1460,
    "mocua": 1467.9,
    "dongcua": 1462.6,
    "caonhat": 1469,
    "thapnhat": 1462.6,
    "biendogiaodong": 6.4,
    "phantrambiendogiaodong": 0.44,
    "khoiluong": "94144",
    "io": 44110,
    "giathanhtoan": 1462.6,
    "khoiluongthoathuan": "10",
    "giatrithoathuan": "1405000000",
    "khoiluongkhoplenh": "94134",
    "giatrikhoplenh": "13790572320000",
    "thaydoisovoingaytruoc": 2.6,
    "phantramthaydoisovoingaytruoc": 0.18,
    "phantramgioihantrongngay": 0.07,
    "gioihancaonhat": 1570.65,
    "gioihanthapnhat": 1365.15,
    "thaydoi": 2.6,
    "phantramthaydoi": 0.18,
    "tongkhoiluong": "0",
    "giatran": 1562.2,
    "giasan": 1357.8,
    "tanggia": 1.1,
    "phantramtanggia": 0.08,
    "giamgia": 5.3,
    "phantramgiamgia": 0.36,
    "biendothaydoi": 6.4,
    "phantrambiendothaydoi": 0.44,
    "tongkhoiluongmua": "0",
    "tongkhoiluongban": "0"
  },
  {
    "id": "20250701-41I1F7000",
    "ngay": "20250701",
    "machungkhoan": "41I1F7000",
    "thamchieu": 1462.6,
    "mocua": 1463.6,
    "dongcua": 1459.2,
    "caonhat": 1468.7,
    "thapnhat": 1456.3,
    "biendogiaodong": 12.4,
    "phantrambiendogiaodong": 0.85,
    "khoiluong": "148706",
    "io": 45639,
    "giathanhtoan": 1459.2,
    "khoiluongthoathuan": "0",
    "giatrithoathuan": "0",
    "khoiluongkhoplenh": "148706",
    "giatrikhoplenh": "21745913670000",
    "thaydoisovoingaytruoc": -3.4,
    "phantramthaydoisovoingaytruoc": -0.23,
    "phantramgioihantrongngay": 0.07,
    "gioihancaonhat": 1566.05,
    "gioihanthapnhat": 1361.15,
    "thaydoi": -3.4,
    "phantramthaydoi": -0.23,
    "tongkhoiluong": "0",
    "giatran": 1564.9,
    "giasan": 1360.3,
    "tanggia": 5.1,
    "phantramtanggia": 0.35,
    "giamgia": 7.3,
    "phantramgiamgia": 0.5,
    "biendothaydoi": 12.4,
    "phantrambiendothaydoi": 0.85,
    "tongkhoiluongmua": "0",
    "tongkhoiluongban": "0"
  },
  {
    "id": "20250702-41I1F7000",
    "ngay": "20250702",
    "machungkhoan": "41I1F7000",
    "thamchieu": 1459.2,
    "mocua": 1461.4,
    "dongcua": 1469.7,
    "caonhat": 1471.8,
    "thapnhat": 1458.7,
    "biendogiaodong": 13.1,
    "phantrambiendogiaodong": 0.9,
    "khoiluong": "156817",
    "io": 47821,
    "giathanhtoan": 1469.7,
    "khoiluongthoathuan": "200",
    "giatrithoathuan": "29095000000",
    "khoiluongkhoplenh": "156617",
    "giatrikhoplenh": "22945691600000",
    "thaydoisovoingaytruoc": 10.5,
    "phantramthaydoisovoingaytruoc": 0.72,
    "phantramgioihantrongngay": 0.07,
    "gioihancaonhat": 1563.7,
    "gioihanthapnhat": 1359.1,
    "thaydoi": 10.5,
    "phantramthaydoi": 0.72,
    "tongkhoiluong": "0",
    "giatran": 1561.3,
    "giasan": 1357.1,
    "tanggia": 10.4,
    "phantramtanggia": 0.71,
    "giamgia": 2.7,
    "phantramgiamgia": 0.18,
    "biendothaydoi": 13.1,
    "phantrambiendothaydoi": 0.89,
    "tongkhoiluongmua": "0",
    "tongkhoiluongban": "0"
  },
  {
    "id": "20250703-41I1F7000",
    "ngay": "20250703",
    "machungkhoan": "41I1F7000",
    "thamchieu": 1469.7,
    "mocua": 1459.9,
    "dongcua": 1471,
    "caonhat": 1479.3,
    "thapnhat": 1454,
    "biendogiaodong": 25.3,
    "phantrambiendogiaodong": 1.74,
    "khoiluong": "220856",
    "io": 52093,
    "giathanhtoan": 1471,
    "khoiluongthoathuan": "110",
    "giatrithoathuan": "16164500000",
    "khoiluongkhoplenh": "220746",
    "giatrikhoplenh": "32457891580000",
    "thaydoisovoingaytruoc": 1.3,
    "phantramthaydoisovoingaytruoc": 0.09,
    "phantramgioihantrongngay": 0.07,
    "gioihancaonhat": 1562.09,
    "gioihanthapnhat": 1357.71,
    "thaydoi": 1.3,
    "phantramthaydoi": 0.09,
    "tongkhoiluong": "0",
    "giatran": 1572.5,
    "giasan": 1366.9,
    "tanggia": 19.4,
    "phantramtanggia": 1.32,
    "giamgia": 5.9,
    "phantramgiamgia": 0.4,
    "biendothaydoi": 25.3,
    "phantrambiendothaydoi": 1.72,
    "tongkhoiluongmua": "16866",
    "tongkhoiluongban": "14847"
  },
  {
    "id": "20250704-41I1F7000",
    "ngay": "20250704",
    "machungkhoan": "41I1F7000",
    "thamchieu": 1471,
    "mocua": 1472,
    "dongcua": 1472.2,
    "caonhat": 1474.8,
    "thapnhat": 1469.4,
    "biendogiaodong": 5.4,
    "phantrambiendogiaodong": 0.37,
    "khoiluong": "122897",
    "io": 58016,
    "giathanhtoan": 1472.2,
    "khoiluongthoathuan": "120",
    "giatrithoathuan": "17580000000",
    "khoiluongkhoplenh": "122777",
    "giatrikhoplenh": "18071866330000",
    "thaydoisovoingaytruoc": 1.2,
    "phantramthaydoisovoingaytruoc": 0.08,
    "phantramgioihantrongngay": 0.07,
    "gioihancaonhat": 1575.04,
    "gioihanthapnhat": 1368.96,
    "thaydoi": 1.2,
    "phantramthaydoi": 0.08,
    "tongkhoiluong": "0",
    "giatran": 1573.9,
    "giasan": 1368.1,
    "tanggia": 2.8,
    "phantramtanggia": 0.19,
    "giamgia": 2.6,
    "phantramgiamgia": 0.18,
    "biendothaydoi": 5.4,
    "phantrambiendothaydoi": 0.37,
    "tongkhoiluongmua": "0",
    "tongkhoiluongban": "0"
  },
  {
    "id": "20250707-41I1F7000",
    "ngay": "20250707",
    "machungkhoan": "41I1F7000",
    "thamchieu": 1472.2,
    "mocua": 1475.6,
    "dongcua": 1492.9,
    "caonhat": 1492.9,
    "thapnhat": 1475.6,
    "biendogiaodong": 17.3,
    "phantrambiendogiaodong": 1.17,
    "khoiluong": "173607",
    "io": 55842,
    "giathanhtoan": 1492.9,
    "khoiluongthoathuan": "122",
    "giatrithoathuan": "17873000000",
    "khoiluongkhoplenh": "173485",
    "giatrikhoplenh": "25740114390000",
    "thaydoisovoingaytruoc": 20.7,
    "phantramthaydoisovoingaytruoc": 1.41,
    "phantramgioihantrongngay": 0.07,
    "gioihancaonhat": 1578.89,
    "gioihanthapnhat": 1372.31,
    "thaydoi": 20.7,
    "phantramthaydoi": 1.41,
    "tongkhoiluong": "0",
    "giatran": 1575.2,
    "giasan": 1369.2,
    "tanggia": 17.3,
    "phantramtanggia": 1.16,
    "giamgia": 0,
    "phantramgiamgia": 0,
    "biendothaydoi": 17.3,
    "phantrambiendothaydoi": 1.16,
    "tongkhoiluongmua": "0",
    "tongkhoiluongban": "0"
  },
  {
    "id": "20250708-41I1F7000",
    "ngay": "20250708",
    "machungkhoan": "41I1F7000",
    "thamchieu": 1492.9,
    "mocua": 1494,
    "dongcua": 1512,
    "caonhat": 1512,
    "thapnhat": 1491,
    "biendogiaodong": 21,
    "phantrambiendogiaodong": 1.41,
    "khoiluong": "181924",
    "io": 59198,
    "giathanhtoan": 1512,
    "khoiluongthoathuan": "240",
    "giatrithoathuan": "35646500000",
    "khoiluongkhoplenh": "181684",
    "giatrikhoplenh": "27239993920000",
    "thaydoisovoingaytruoc": 19.1,
    "phantramthaydoisovoingaytruoc": 1.28,
    "phantramgioihantrongngay": 0.07,
    "gioihancaonhat": 1598.58,
    "gioihanthapnhat": 1389.42,
    "thaydoi": 19.1,
    "phantramthaydoi": 1.28,
    "tongkhoiluong": "0",
    "giatran": 1597.4,
    "giasan": 1388.4,
    "tanggia": 18,
    "phantramtanggia": 1.19,
    "giamgia": 3,
    "phantramgiamgia": 0.2,
    "biendothaydoi": 21,
    "phantrambiendothaydoi": 1.39,
    "tongkhoiluongmua": "15460",
    "tongkhoiluongban": "15275"
  },
  {
    "id": "20250709-41I1F7000",
    "ngay": "20250709",
    "machungkhoan": "41I1F7000",
    "thamchieu": 1512,
    "mocua": 1513,
    "dongcua": 1533,
    "caonhat": 1534.5,
    "thapnhat": 1513,
    "biendogiaodong": 21.5,
    "phantrambiendogiaodong": 1.42,
    "khoiluong": "246252",
    "io": 61514,
    "giathanhtoan": 1533,
    "khoiluongthoathuan": "328",
    "giatrithoathuan": "49292800000",
    "khoiluongkhoplenh": "245924",
    "giatrikhoplenh": "37530404290000",
    "thaydoisovoingaytruoc": 21,
    "phantramthaydoisovoingaytruoc": 1.39,
    "phantramgioihantrongngay": 0.07,
    "gioihancaonhat": 1618.91,
    "gioihanthapnhat": 1407.09,
    "thaydoi": 21,
    "phantramthaydoi": 1.39,
    "tongkhoiluong": "0",
    "giatran": 1617.8,
    "giasan": 1406.2,
    "tanggia": 21.5,
    "phantramtanggia": 1.4,
    "giamgia": 0,
    "phantramgiamgia": 0,
    "biendothaydoi": 21.5,
    "phantrambiendothaydoi": 1.4,
    "tongkhoiluongmua": "19158",
    "tongkhoiluongban": "18563"
  },
  {
    "id": "20250710-41I1F7000",
    "ngay": "20250710",
    "machungkhoan": "41I1F7000",
    "thamchieu": 1533,
    "mocua": 1537.5,
    "dongcua": 1567.9,
    "caonhat": 1639.9,
    "thapnhat": 1535.6,
    "biendogiaodong": 104.3,
    "phantrambiendogiaodong": 6.79,
    "khoiluong": "220181",
    "io": 52394,
    "giathanhtoan": 1567.9,
    "khoiluongthoathuan": "240",
    "giatrithoathuan": "36720500000",
    "khoiluongkhoplenh": "219941",
    "giatrikhoplenh": "34060860290000",
    "thaydoisovoingaytruoc": 34.9,
    "phantramthaydoisovoingaytruoc": 2.28,
    "phantramgioihantrongngay": 0.07,
    "gioihancaonhat": 1645.13,
    "gioihanthapnhat": 1429.87,
    "thaydoi": 34.9,
    "phantramthaydoi": 2.28,
    "tongkhoiluong": "0",
    "giatran": 1640.3,
    "giasan": 1425.7,
    "tanggia": 102.4,
    "phantramtanggia": 6.53,
    "giamgia": 1.9,
    "phantramgiamgia": 0.12,
    "biendothaydoi": 104.3,
    "phantrambiendothaydoi": 6.65,
    "tongkhoiluongmua": "16561",
    "tongkhoiluongban": "16177"
  },
  {
    "id": "20250711-41I1F7000",
    "ngay": "20250711",
    "machungkhoan": "41I1F7000",
    "thamchieu": 1567.9,
    "mocua": 1571.7,
    "dongcua": 1595.9,
    "caonhat": 1602.5,
    "thapnhat": 1571.3,
    "biendogiaodong": 31.2,
    "phantrambiendogiaodong": 1.99,
    "khoiluong": "249030",
    "io": 49996,
    "giathanhtoan": 1595.9,
    "khoiluongthoathuan": "0",
    "giatrithoathuan": "0",
    "khoiluongkhoplenh": "249030",
    "giatrikhoplenh": "39476210320000",
    "thaydoisovoingaytruoc": 28,
    "phantramthaydoisovoingaytruoc": 1.79,
    "phantramgioihantrongngay": 0.07,
    "gioihancaonhat": 1681.72,
    "gioihanthapnhat": 1461.68,
    "thaydoi": 28,
    "phantramthaydoi": 1.79,
    "tongkhoiluong": "0",
    "giatran": 1677.6,
    "giasan": 1458.2,
    "tanggia": 30.8,
    "phantramtanggia": 1.93,
    "giamgia": 0.4,
    "phantramgiamgia": 0.03,
    "biendothaydoi": 31.2,
    "phantrambiendothaydoi": 1.96,
    "tongkhoiluongmua": "0",
    "tongkhoiluongban": "0"
  },
  {
    "id": "20250714-41I1F7000",
    "ngay": "20250714",
    "machungkhoan": "41I1F7000",
    "thamchieu": 1595.9,
    "mocua": 1600.5,
    "dongcua": 1601.2,
    "caonhat": 1608.5,
    "thapnhat": 1570,
    "biendogiaodong": 38.5,
    "phantrambiendogiaodong": 2.45,
    "khoiluong": "291109",
    "io": 38657,
    "giathanhtoan": 1601.2,
    "khoiluongthoathuan": "220",
    "giatrithoathuan": "35110000000",
    "khoiluongkhoplenh": "290889",
    "giatrikhoplenh": "46396352040000",
    "thaydoisovoingaytruoc": 5.3,
    "phantramthaydoisovoingaytruoc": 0.33,
    "phantramgioihantrongngay": 0.07,
    "gioihancaonhat": 1712.54,
    "gioihanthapnhat": 1488.46,
    "thaydoi": 5.3,
    "phantramthaydoi": 0.33,
    "tongkhoiluong": "0",
    "giatran": 1707.6,
    "giasan": 1484.2,
    "tanggia": 8,
    "phantramtanggia": 0.5,
    "giamgia": 30.5,
    "phantramgiamgia": 1.9,
    "biendothaydoi": 38.5,
    "phantrambiendothaydoi": 2.4,
    "tongkhoiluongmua": "0",
    "tongkhoiluongban": "0"
  },
  {
    "id": "20250715-41I1F7000",
    "ngay": "20250715",
    "machungkhoan": "41I1F7000",
    "thamchieu": 1601.2,
    "mocua": 1606,
    "dongcua": 1594,
    "caonhat": 1611.8,
    "thapnhat": 1594,
    "biendogiaodong": 17.8,
    "phantrambiendogiaodong": 1.12,
    "khoiluong": "172414",
    "io": 40790,
    "giathanhtoan": 1594,
    "khoiluongthoathuan": "0",
    "giatrithoathuan": "0",
    "khoiluongkhoplenh": "172414",
    "giatrikhoplenh": "27658538370000",
    "thaydoisovoingaytruoc": -7.2,
    "phantramthaydoisovoingaytruoc": -0.45,
    "phantramgioihantrongngay": 0.07,
    "gioihancaonhat": 1718.42,
    "gioihanthapnhat": 1493.58,
    "thaydoi": -7.2,
    "phantramthaydoi": -0.45,
    "tongkhoiluong": "0",
    "giatran": 1713.2,
    "giasan": 1489.2,
    "tanggia": 5.8,
    "phantramtanggia": 0.36,
    "giamgia": 12,
    "phantramgiamgia": 0.75,
    "biendothaydoi": 17.8,
    "phantrambiendothaydoi": 1.11,
    "tongkhoiluongmua": "14580",
    "tongkhoiluongban": "13712"
  },
  {
    "id": "20250716-41I1F7000",
    "ngay": "20250716",
    "machungkhoan": "41I1F7000",
    "thamchieu": 1594,
    "mocua": 1592.3,
    "dongcua": 1618,
    "caonhat": 1619,
    "thapnhat": 1590.3,
    "biendogiaodong": 28.7,
    "phantrambiendogiaodong": 1.8,
    "khoiluong": "186554",
    "io": 37562,
    "giathanhtoan": 1618,
    "khoiluongthoathuan": "100",
    "giatrithoathuan": "15940000000",
    "khoiluongkhoplenh": "186454",
    "giatrikhoplenh": "29874767030000",
    "thaydoisovoingaytruoc": 24,
    "phantramthaydoisovoingaytruoc": 1.51,
    "phantramgioihantrongngay": 0.07,
    "gioihancaonhat": 1703.76,
    "gioihanthapnhat": 1480.84,
    "thaydoi": 24,
    "phantramthaydoi": 1.51,
    "tongkhoiluong": "0",
    "giatran": 1705.5,
    "giasan": 1482.5,
    "tanggia": 26.7,
    "phantramtanggia": 1.65,
    "giamgia": 2,
    "phantramgiamgia": 0.12,
    "biendothaydoi": 28.7,
    "phantrambiendothaydoi": 1.77,
    "tongkhoiluongmua": "14036",
    "tongkhoiluongban": "15673"
  },
  {
    "id": "20250717-41I1F7000",
    "ngay": "20250717",
    "machungkhoan": "41I1F7000",
    "thamchieu": 1618,
    "mocua": 1621.5,
    "dongcua": 1638,
    "caonhat": 1644.5,
    "thapnhat": 1619.3,
    "biendogiaodong": 25.2,
    "phantrambiendogiaodong": 1.56,
    "khoiluong": "205509",
    "io": 32405,
    "giathanhtoan": 1638,
    "khoiluongthoathuan": "100",
    "giatrithoathuan": "16180000000",
    "khoiluongkhoplenh": "205409",
    "giatrikhoplenh": "33556607940000",
    "thaydoisovoingaytruoc": 20,
    "phantramthaydoisovoingaytruoc": 1.24,
    "phantramgioihantrongngay": 0.07,
    "gioihancaonhat": 1735.01,
    "gioihanthapnhat": 1507.99,
    "thaydoi": 20,
    "phantramthaydoi": 1.24,
    "tongkhoiluong": "0",
    "giatran": 1731.2,
    "giasan": 1504.8,
    "tanggia": 23,
    "phantramtanggia": 1.4,
    "giamgia": 2.2,
    "phantramgiamgia": 0.13,
    "biendothaydoi": 25.2,
    "phantrambiendothaydoi": 1.53,
    "tongkhoiluongmua": "0",
    "tongkhoiluongban": "0"
  }
]